codegraph/__init__.py
codegraph/core.py
codegraph/main.py
codegraph/parser.py
codegraph/templates/index.html
codegraph/templates/main.js
codegraph/templates/styles.css
codegraph/utils.py
codegraph/vizualyzer.py
codegraph-1.2.0.dist-info/METADATA
codegraph-1.2.0.dist-info/WHEEL
codegraph-1.2.0.dist-info/entry_points.txt
codegraph-1.2.0.dist-info/licenses/LICENSE
codegraph-1.2.0.dist-info/RECORD
