Metadata-Version: 2.4
Name: codegraph
Version: 1.2.0
Summary: Tool that create a graph of code to show dependencies between code entities (methods, classes and etc).
License: MIT
License-File: LICENSE
Author: xnuinside
Author-email: xnuinside@gmail.com
Requires-Python: >=3.9,<4.0
Classifier: License :: OSI Approved :: MIT License
Classifier: Programming Language :: Python :: 3
Classifier: Programming Language :: Python :: 3.9
Classifier: Programming Language :: Python :: 3.10
Classifier: Programming Language :: Python :: 3.11
Classifier: Programming Language :: Python :: 3.12
Classifier: Programming Language :: Python :: 3.13
Classifier: Programming Language :: Python :: 3.14
Classifier: Topic :: Software Development
Classifier: Topic :: Software Development :: Libraries
Classifier: Topic :: Software Development :: Libraries :: Python Modules
Classifier: Topic :: Utilities
Provides-Extra: matplotlib
Requires-Dist: click (>=8.0)
Requires-Dist: matplotlib (>=3.5) ; extra == "matplotlib"
Requires-Dist: networkx (>=2.8) ; extra == "matplotlib"
Project-URL: Homepage, https://github.com/xnuinside/codegraph
Project-URL: Repository, https://github.com/xnuinside/codegraph
